sneaky_s0ng/__init__.py
sneaky_s0ng/encrypt.py
sneaky_s0ng/music.py
sneaky_s0ng/ver2.py
sneaky_s0ng-2.1.4b0.dist-info/LICENSE
sneaky_s0ng-2.1.4b0.dist-info/METADATA
sneaky_s0ng-2.1.4b0.dist-info/WHEEL
sneaky_s0ng-2.1.4b0.dist-info/top_level.txt
sneaky_s0ng-2.1.4b0.dist-info/RECORD
