Metadata-Version: 2.1
Name: sneaky_s0ng
Version: 2.1.4b0
Summary: A Python package for encrypting English and German to music notation.
Home-page: https://magicat8.github.io
Author: Cameron
Author-email: magicat8bill@gmail.com
License: MIT
Project-URL: Documentation, https://github.com/Magicat8bill/Sneaky-S0ng/tree/main
Classifier: Programming Language :: Python :: 3
Classifier: License :: OSI Approved :: MIT License
Classifier: Operating System :: OS Independent
Requires-Python: >=3.8
License-File: LICENSE
Requires-Dist: music21 >=9.1.0
